storyblok_assets_cleanup.py
storyblok_assets_cleanup-1.0.2.dist-info/LICENSE
storyblok_assets_cleanup-1.0.2.dist-info/METADATA
storyblok_assets_cleanup-1.0.2.dist-info/WHEEL
storyblok_assets_cleanup-1.0.2.dist-info/entry_points.txt
storyblok_assets_cleanup-1.0.2.dist-info/top_level.txt
storyblok_assets_cleanup-1.0.2.dist-info/RECORD
