Metadata-Version: 2.1
Name: storyblok-assets-cleanup
Version: 1.0.2
Summary: Utility to clean unused storyblok assets.
Home-page: https://github.com/significa/storyblok-assets-cleanup
Author: Significa
License: MIT
Keywords: storyblok
Classifier: Development Status :: 4 - Beta
Classifier: Environment :: Console
Classifier: Intended Audience :: Developers
Classifier: License :: OSI Approved :: MIT License
Classifier: Topic :: Utilities
Classifier: Programming Language :: Python :: 3
Classifier: Programming Language :: Python :: 3.9
Classifier: Programming Language :: Python :: 3.10
Classifier: Programming Language :: Python :: 3.11
License-File: LICENSE
Requires-Dist: requests==2.32.3
